vipwrap/__init__.py
vipwrap/gdi.py
vipwrap/models.py
vipwrap-0.1.5.dist-info/licenses/LICENSE
vipwrap-0.1.5.dist-info/METADATA
vipwrap-0.1.5.dist-info/WHEEL
vipwrap-0.1.5.dist-info/top_level.txt
vipwrap-0.1.5.dist-info/RECORD
