Metadata-Version: 2.4
Name: vipwrap
Version: 0.1.5
Summary: Python package that allows interacting with VIP.
Home-page: https://github.com/pepsimidamerica/vipwrap
Author: Jordan Maynor
Author-email: jmaynor@pepsimidamerica.com
Classifier: Programming Language :: Python :: 3
Classifier: License :: OSI Approved :: The Unlicense (Unlicense)
Classifier: Operating System :: OS Independent
Requires-Python: >=3.12
License-File: LICENSE
Requires-Dist: paramiko
Requires-Dist: pandas
Requires-Dist: pandera
Dynamic: author
Dynamic: author-email
Dynamic: classifier
Dynamic: description
Dynamic: description-content-type
Dynamic: home-page
Dynamic: license-file
Dynamic: requires-dist
Dynamic: requires-python
Dynamic: summary
